cd2t/__init__.py
cd2t/data_parser.py
cd2t/errors.py
cd2t/references.py
cd2t/results.py
cd2t/run_time_env.py
cd2t/schema.py
cd2t/utils.py
cd2t/types/__init__.py
cd2t/types/base.py
cd2t/types/bool.py
cd2t/types/datatype.py
cd2t/types/enum.py
cd2t/types/float.py
cd2t/types/fqdn.py
cd2t/types/hostname.py
cd2t/types/idlist.py
cd2t/types/integer.py
cd2t/types/ip.py
cd2t/types/list.py
cd2t/types/multitype.py
cd2t/types/none.py
cd2t/types/object.py
cd2t/types/parser.py
cd2t/types/schema.py
cd2t/types/string.py
cd2t-2.2.2.dist-info/METADATA
cd2t-2.2.2.dist-info/WHEEL
cd2t-2.2.2.dist-info/licenses/LICENSE
cd2t-2.2.2.dist-info/RECORD
