Metadata-Version: 2.3
Name: cd2t
Version: 2.2.2
Summary: cd2t validates data structure, data types and values with templates
Project-URL: Homepage, https://gitlab.com/ko.no/cd2t
Project-URL: Bug Tracker, https://gitlab.com/ko.no/cd2t/-/issues
Author-email: Korte Noack <korte@8lacht.de>
License-File: LICENSE
Classifier: Development Status :: 5 - Production/Stable
Classifier: Intended Audience :: Developers
Classifier: License :: OSI Approved :: GNU General Public License v3 (GPLv3)
Classifier: Operating System :: OS Independent
Classifier: Programming Language :: Python :: 3.9
Requires-Python: >=3.9
